pldag_solver_sdk/__init__.py
pldag_solver_sdk-0.2.2.dist-info/METADATA
pldag_solver_sdk-0.2.2.dist-info/WHEEL
pldag_solver_sdk-0.2.2.dist-info/RECORD
