Metadata-Version: 2.1
Name: pldag-solver-sdk
Version: 0.2.2
Summary: Python SDK package for Solver API
Author: znittzel
Author-email: rikard@ourstudio.se
Requires-Python: >=3.10,<4.0
Classifier: Programming Language :: Python :: 3
Classifier: Programming Language :: Python :: 3.10
Classifier: Programming Language :: Python :: 3.11
Classifier: Programming Language :: Python :: 3.12
Classifier: Programming Language :: Python :: 3.13
Requires-Dist: aiohttp (>=3.11.6,<4.0.0)
Requires-Dist: pldag (>=0.10.11,<0.11.0)
